jsonformat/__init__.py
jsonformat/jsonformat.py
jsonformat-0.0.11.dist-info/METADATA
jsonformat-0.0.11.dist-info/WHEEL
jsonformat-0.0.11.dist-info/entry_points.txt
jsonformat-0.0.11.dist-info/top_level.txt
jsonformat-0.0.11.dist-info/RECORD
